gradient_labs/__init__.py
gradient_labs/_article_delete.py
gradient_labs/_article_set_status.py
gradient_labs/_article_topic_upsert.py
gradient_labs/_article_upsert.py
gradient_labs/_conversation_add_message.py
gradient_labs/_conversation_add_resource.py
gradient_labs/_conversation_assign.py
gradient_labs/_conversation_cancel.py
gradient_labs/_conversation_event.py
gradient_labs/_conversation_finish.py
gradient_labs/_conversation_rate.py
gradient_labs/_conversation_read.py
gradient_labs/_conversation_resume.py
gradient_labs/_conversation_start.py
gradient_labs/_handoff_target_delete.py
gradient_labs/_handoff_target_set_default.py
gradient_labs/_handoff_target_upsert.py
gradient_labs/_handoff_targets.py
gradient_labs/_http_client.py
gradient_labs/_pagination.py
gradient_labs/_procedure_list.py
gradient_labs/_procedure_read.py
gradient_labs/_procedure_set_limit.py
gradient_labs/_tool_create.py
gradient_labs/_tool_delete.py
gradient_labs/_tool_execute.py
gradient_labs/_tool_list.py
gradient_labs/_tool_read.py
gradient_labs/_tool_update.py
gradient_labs/article.py
gradient_labs/client.py
gradient_labs/conversation.py
gradient_labs/errors.py
gradient_labs/handoff_target.py
gradient_labs/procedure.py
gradient_labs/py.typed
gradient_labs/tool.py
gradient_labs/webhook.py
gradient_labs-0.11.4.dist-info/METADATA
gradient_labs-0.11.4.dist-info/WHEEL
gradient_labs-0.11.4.dist-info/RECORD
