Metadata-Version: 2.4
Name: gradient-labs
Version: 0.11.4
Summary: Python bindings for the Gradient Labs API
Requires-Python: <4.0,>=3.9
Requires-Dist: dataclasses-json>=0.6.7
Requires-Dist: marshmallow>=3.25.0
Requires-Dist: pytest>=8.3.4
Requires-Dist: pytz>=2024.2
Requires-Dist: requests>=2.32.3
Requires-Dist: ruff>=0.9.1
